README.md
setup.cfg
setup.py
celebrity_births_test_luke.egg-info/PKG-INFO
celebrity_births_test_luke.egg-info/SOURCES.txt
celebrity_births_test_luke.egg-info/dependency_links.txt
celebrity_births_test_luke.egg-info/requires.txt
celebrity_births_test_luke.egg-info/top_level.txt
project/__init__.py
project/celebrities_births.py
test/test_project.py