Metadata-Version: 1.0
Name: celebrity-births-test-luke
Version: 0.0.1
Summary: Mock package that allows you to find celebrity by date of birth
Home-page: https://github.com/Lugar95/Test-Package.git
Author: Luke Gardiner
Author-email: UNKNOWN
License: MIT
Platform: UNKNOWN
